adalib_auth/__init__.py
adalib_auth/config/__init__.py
adalib_auth/config/config.py
adalib_auth/jupyterhub/__init__.py
adalib_auth/jupyterhub/jupyterhub.py
adalib_auth/keycloak/__init__.py
adalib_auth/keycloak/keycloak.py
adalib_auth-1.3.0.dist-info/METADATA
adalib_auth-1.3.0.dist-info/WHEEL
adalib_auth-1.3.0.dist-info/RECORD
