Metadata-Version: 2.1
Name: adalib-auth
Version: 1.3.0
Summary: The programmatic tool to authenticate with AdaLab.
Home-page: https://adamatics.com
Author: Adamatics ApS
Author-email: info@adamatics.com
Requires-Python: >=3.10.0,<4.0.0
Classifier: Development Status :: 4 - Beta
Classifier: Intended Audience :: Developers
Classifier: Operating System :: OS Independent
Classifier: Programming Language :: Python
Classifier: Programming Language :: Python :: 3
Classifier: Programming Language :: Python :: 3.10
Classifier: Programming Language :: Python :: 3.11
Classifier: Programming Language :: Python :: 3.12
Classifier: Topic :: Software Development :: Libraries :: Python Modules
Classifier: Typing :: Typed
Requires-Dist: python-keycloak (>=3.3.0)
Requires-Dist: requests-oauthlib (>=1.3.1)
Project-URL: Repository, https://gitlab.com/adamatics/python/adalib-auth
